{
  "Workflows": [
    {
      "Path": null,
      "SortBy": 0,
      "VariablesSectionElementsOrder": [],
      "ArgumentsSectionElementsOrder": null,
      "ConstantsSectionElementsOrder": [],
      "AddedNamespaces": null
    },
    {
      "Path": "Main.xaml",
      "SortBy": 0,
      "VariablesSectionElementsOrder": [
        "SheetName&Sequence_1",
        "Date_Time&Sequence_1",
        "DT_Config&Sequence_1",
        "Config&Sequence_1",
        "Dt_master&Sequence_1"
      ],
      "ArgumentsSectionElementsOrder": [],
      "ConstantsSectionElementsOrder": [],
      "AddedNamespaces": null
    },
    {
      "Path": "LG_Oven_DataScraping.xaml",
      "SortBy": 0,
      "VariablesSectionElementsOrder": [
        "OvenName_LG&Sequence_20",
        "OvenURL_LG&Sequence_20",
        "OfferPrice_LG&Sequence_20",
        "ModelNumber_LG&Sequence_20",
        "MRP_LG&Sequence_20",
        "OvenName_LG&Sequence_11",
        "OvenURL_LG&Sequence_11",
        "OfferPrice_LG&Sequence_11",
        "ModelNumber_LG&Sequence_11",
        "MRP_LG&Sequence_11",
        "Dt_Ovens&Sequence_6",
        "browser&Sequence_6",
        "Dt_Report&Sequence_6",
        "MRP_LG&Sequence_7",
        "ModelNumber_LG&Sequence_7",
        "OfferPrice_LG&Sequence_7",
        "OvenURL_LG&Sequence_7",
        "OvenName_LG&Sequence_7"
      ],
      "ArgumentsSectionElementsOrder": [
        "In_ReportSheetName",
        "In_OvenType",
        "In_ReportPath",
        "In_URL",
        "Config"
      ],
      "ConstantsSectionElementsOrder": [],
      "AddedNamespaces": null
    },
    {
      "Path": "test.xaml",
      "SortBy": 0,
      "VariablesSectionElementsOrder": [
        "Type&Sequence_9",
        "ChildLock&Sequence_9",
        "DefrostMode&Sequence_9",
        "PreheatMode&Sequence_9",
        "CavityMaterial&Sequence_9",
        "PowerOutput&Sequence_9",
        "ProductDimension&Sequence_9",
        "Color&Sequence_9",
        "OvenCapacity&Sequence_9",
        "SamsungSpecsDict&Sequence_9",
        "ExtractDataTable&Sequence_8",
        "ExtractDataTable&Sequence_2"
      ],
      "ArgumentsSectionElementsOrder": [],
      "ConstantsSectionElementsOrder": [],
      "AddedNamespaces": null
    },
    {
      "Path": "SamsungDataScraping.xaml",
      "SortBy": 0,
      "VariablesSectionElementsOrder": [
        "Dt_Report&Sequence_1",
        "browser&Sequence_1",
        "Dt_Ovens&Sequence_1",
        "OvenName_LG&Sequence_3",
        "OvenURL_LG&Sequence_3",
        "OfferPrice_LG&Sequence_3",
        "ModelNumber_LG&Sequence_3",
        "MRP_LG&Sequence_3"
      ],
      "ArgumentsSectionElementsOrder": [
        "In_ReportSheetName",
        "In_OvenType",
        "In_ReportPath",
        "In_URL",
        "Config"
      ],
      "ConstantsSectionElementsOrder": [],
      "AddedNamespaces": null
    },
    {
      "Path": "Bot_1.xaml",
      "SortBy": 0,
      "VariablesSectionElementsOrder": [
        "Dt_main&Sequence_12",
        "Dt_bot1&Sequence_12"
      ],
      "ArgumentsSectionElementsOrder": [
        "Dt_master",
        "Config",
        "Date_Time"
      ],
      "ConstantsSectionElementsOrder": [],
      "AddedNamespaces": null
    },
    {
      "Path": "Frameworks/LGScraping.xaml",
      "SortBy": 0,
      "VariablesSectionElementsOrder": [
        "OvenCapacityLG&Sequence_2",
        "ColorLG&Sequence_2",
        "ProductDimensionLG&Sequence_2",
        "PowerOutputLG&Sequence_2",
        "CavityMaterialLG&Sequence_2",
        "Raiting&Sequence_2",
        "DefrostLG&Sequence_2",
        "ChildLockLG&Sequence_2",
        "TypeLG&Sequence_2",
        "DT_LG&Sequence_2",
        "RowIndex&Sequence_2"
      ],
      "ArgumentsSectionElementsOrder": [],
      "ConstantsSectionElementsOrder": [],
      "AddedNamespaces": null
    },
    {
      "Path": "Bot_4.xaml",
      "SortBy": 0,
      "VariablesSectionElementsOrder": [
        "RowIndex&Sequence_13",
        "Dt_SamsungSpecs&Sequence_21",
        "SamsungSpecsDict&Sequence_21",
        "OvenCapacity&Sequence_21",
        "Color&Sequence_21",
        "ProductDimension&Sequence_21",
        "PowerOutput&Sequence_21",
        "CavityMaterial&Sequence_21",
        "PreheatMode&Sequence_21",
        "DefrostMode&Sequence_21",
        "ChildLock&Sequence_21",
        "Type&Sequence_21",
        "Dt_InputBot4&Sequence_13",
        "bot4Browser&Sequence_15",
        "OvenCapacityLG&Sequence_17",
        "ColorLG&Sequence_17",
        "ProductDimensionLG&Sequence_17",
        "PowerOutputLG&Sequence_17",
        "CavityMaterialLG&Sequence_17",
        "Raiting&Sequence_17",
        "DefrostLG&Sequence_17",
        "ChildLockLG&Sequence_17",
        "TypeLG&Sequence_17",
        "WarmLG&Sequence_17"
      ],
      "ArgumentsSectionElementsOrder": [
        "Config",
        "Date_Time",
        "SheetName"
      ],
      "ConstantsSectionElementsOrder": [],
      "AddedNamespaces": null
    }
  ]
}